{
  "timestamp": "2025-10-07T20:02:01.165969",
  "user_request": "white shirts",
  "total_original": 10,
  "total_kept": 10,
  "total_filtered": 0,
  "overall_filtering_rate": "0.0%",
  "store_analysis": {
    "CultureKings": {
      "original_count": 7,
      "kept_count": 7,
      "filtered_count": 0,
      "filtering_rate": "0.0%",
      "kept_rate": "100.0%"
    },
    "Universal Store": {
      "original_count": 3,
      "kept_count": 3,
      "filtered_count": 0,
      "filtering_rate": "0.0%",
      "kept_rate": "100.0%"
    }
  },
  "kept_products": [
    {
      "name": "Adidas Chip In NYC Graphic T-Shirt White",
      "price": "$60.00",
      "brand": "CultureKings",
      "url": "https://culturekings.com.au/products/adidas-chip-in-nyc-graphic-t-shirt-white-mens",
      "image_url": "https://cdn.shopify.com/s/files/1/1023/3455/files/02055381-YW100_mens_0010.jpg?v=1759266806",
      "store_name": "CultureKings",
      "is_on_sale": null,
      "extracted_at": "2025-10-07T20:01:58.497789"
    },
    {
      "name": "Adidas Teamgeist T-Shirt White/Black",
      "price": "$60.00",
      "brand": "CultureKings",
      "url": "https://culturekings.com.au/products/adidas-teamgeist-t-shirt-white-black-mens",
      "image_url": "https://cdn.shopify.com/s/files/1/1023/3455/files/02054742-YW110_mens_0010.jpg?v=1759267966",
      "store_name": "CultureKings",
      "is_on_sale": null,
      "extracted_at": "2025-10-07T20:01:58.497795"
    },
    {
      "name": "American Thrift Block Fit T-Shirt Off White",
      "price": "$29.95",
      "brand": "CultureKings",
      "url": "https://culturekings.com.au/products/american-thrift-the-block-fit-t-shirt-off-white-mens",
      "image_url": "https://cdn.shopify.com/s/files/1/1023/3455/files/02055502-YO007_mens_0010.jpg?v=1759363410",
      "store_name": "CultureKings",
      "is_on_sale": null,
      "extracted_at": "2025-10-07T20:01:58.497773"
    },
    {
      "name": "American Thrift Block Fit T-Shirt White",
      "price": "$29.95",
      "brand": "CultureKings",
      "url": "https://culturekings.com.au/products/american-thrift-the-block-fit-t-shirt-white-mens",
      "image_url": "https://cdn.shopify.com/s/files/1/1023/3455/files/02055502-YW100_mens_0010.jpg?v=1759363434",
      "store_name": "CultureKings",
      "is_on_sale": null,
      "extracted_at": "2025-10-07T20:01:58.497764"
    },
    {
      "name": "American Thrift New Standard T-Shirt White",
      "price": "$29.95",
      "brand": "CultureKings",
      "url": "https://culturekings.com.au/products/american-thrift-new-standard-t-shirt-white-mens",
      "image_url": "https://cdn.shopify.com/s/files/1/1023/3455/files/02055504-YW100_mens_0010.jpg?v=1759363593",
      "store_name": "CultureKings",
      "is_on_sale": null,
      "extracted_at": "2025-10-07T20:01:58.497744"
    },
    {
      "name": "New Era Detroit Tigers Paisley Oversized T-Shirt White",
      "price": "$70.00",
      "brand": "CultureKings",
      "url": "https://culturekings.com.au/products/new-era-detroit-tigers-paisley-oversized-t-shirt-white-mens",
      "image_url": "https://cdn.shopify.com/s/files/1/1023/3455/files/02053088-YW100_mens_0010.jpg?v=1758672601",
      "store_name": "CultureKings",
      "is_on_sale": null,
      "extracted_at": "2025-10-07T20:01:58.497814"
    },
    {
      "name": "New Era New York Yankees Paisley Oversized T-Shirt White",
      "price": "$70.00",
      "brand": "CultureKings",
      "url": "https://culturekings.com.au/products/new-era-new-york-yankees-paisley-oversized-t-shirt-white-mens",
      "image_url": "https://cdn.shopify.com/s/files/1/1023/3455/files/02053091-YW100_mens_0010.jpg?v=1758672838",
      "store_name": "CultureKings",
      "is_on_sale": null,
      "extracted_at": "2025-10-07T20:01:58.497809"
    },
    {
      "name": "Alfie Boxy Polo White",
      "price": "$68.00",
      "brand": "Universal Store",
      "url": "https://www.universalstore.com/collections/mens-shirts-polos/products/common-need-alaric-boxy-polo-white",
      "image_url": "https://www.universalstore.com/cdn/shop/files/411930_US_003.jpg?width=1200&height=1200&v=1759219162",
      "store_name": "Universal Store",
      "is_on_sale": false,
      "extracted_at": "2025-10-07T20:01:58.452262"
    },
    {
      "name": "Bloomed Linen Resort Shirt White",
      "price": "$75.00",
      "brand": "Universal Store",
      "url": "https://www.universalstore.com/collections/mens-shirts-polos/products/common-need-bloomed-linen-resort-shirt-white",
      "image_url": "https://www.universalstore.com/cdn/shop/files/411243_US_000.jpg?width=1200&height=1200&v=1758779355",
      "store_name": "Universal Store",
      "is_on_sale": false,
      "extracted_at": "2025-10-07T20:01:58.451164"
    },
    {
      "name": "Token Boxy Cropped Resort Shirt White",
      "price": "$68.00",
      "brand": "Universal Store",
      "url": "https://www.universalstore.com/collections/mens-shirts-polos/products/common-need-token-boxy-cropped-resort-shirt-white",
      "image_url": "https://www.universalstore.com/cdn/shop/files/411925_US_000.jpg?width=1200&height=1200&v=1759219284",
      "store_name": "Universal Store",
      "is_on_sale": false,
      "extracted_at": "2025-10-07T20:01:58.452476"
    }
  ],
  "filtered_products": [],
  "kept_indices": [
    0,
    1,
    2,
    3,
    4,
    5,
    6,
    7,
    8,
    9
  ]
}